[
    {
        "title": "Renaissance Fair Peter Pan",
        "description": "Fashionable cosplay, peter pan, elf",
        "URL": "https://i.pinimg.com/474x/b1/12/9f/b1129fe005256b5ecce51f00eb380fb5.jpg"
    },
    {
        "title": "Firebending Poses",
        "description": "Art References for Firebending ATLA Avatar the Last Airbender Drawing",
        "URL": "https://i.pinimg.com/474x/31/46/06/3146067b6f9b116dcff0a89b16e833d5.jpg"
    },
    {
        "title": "",
        "description": "",
        "URL": "https://i.pinimg.com/474x/17/58/67/175867314bc6cf794b3926a22577b189.jpg"
    },
    {
        "title": "jorts @ uni on Twitter",
        "description": "can't sleep, can't focus, draws guitar instead",
        "URL": "https://i.pinimg.com/564x/09/74/54/0974541177c0ff0ed302421a754dc18e.jpg"
    },
    {
        "title": "mouse warrior , HONG XIANG HUANG",
        "description": "done for CDC ArtStation",
        "URL": "https://i.pinimg.com/564x/7f/04/27/7f0427ceba326c2665a2bf8b03698c13.jpg"
    },
    {
        "title": "fairy cat",
        "description": "fairy cat in flower field",
        "URL": "https://i.pinimg.com/564x/e1/8b/c0/e18bc04ae5ff7b5023c8d73766caf047.jpg"
    },
    {
        "title": "https://i.pinimg.com/564x/e1/8b/c0/e18bc04ae5ff7b5023c8d73766caf047.jpg",
        "description": "",
        "URL": "https://i.pinimg.com/474x/89/56/a1/8956a199a913cfa5a4a8696e6f08f821.jpg"
    },
    {
        "title": "Earl on Twitter",
        "description": "they're on a vacation! #renga #sk8theinfinity",
        "URL": "https://i.pinimg.com/564x/08/90/48/089048a43483ebfcec0544e9e3f85900.jpg"
    },
    {
        "title": "Quiet Time, Minnie zhou",
        "description": "Have not worked on a personal piece in a long, long time. It was fun treating myself as the client, and just doing whatever I wanted!",
        "URL": "https://i.pinimg.com/564x/47/64/78/476478da4a76c3ff3f052db8cc674dc4.jpg"
    },
    {
        "title": "A little concept, GZQ seven",
        "description": "Some of the concepts I painted recently, The Shadow of your Smile by Astrud Gilberto gave me a lot of imagination. There is a touch of sadness in the sincere singing.",
        "URL": "https://i.pinimg.com/564x/b7/d1/1a/b7d11a03cf7adcce9eff48f78cc99be3.jpg"
    },
    {
        "title": "",
        "description": "",
        "URL": "https://i.pinimg.com/564x/55/d5/fa/55d5fa46b404259f6fd8af9acd920fa3.jpg"
    },
    {
        "title": "Anime Girl",
        "description": "Tokyo Otaku",
        "URL": "https://i.pinimg.com/564x/82/46/35/824635760f7ca0c2e63631f485822c52.jpg"
    },
    {
        "title": "KAYLA",
        "description": "Kayla hadlington by Kali Ledger",
        "URL": "https://i.pinimg.com/564x/7f/2e/e0/7f2ee027d9199463fe869e7b7fa16e06.jpg"
    },
    {
        "title": "Ash Thorp on Twitter",
        "description": "Metal Gear Solid - Gray Fox - GRAY 2014",
        "URL": "https://i.pinimg.com/564x/a0/13/79/a01379101b7424dfbd86bd7fe0743e30.jpg"
    },
    {
        "title": "",
        "description": "",
        "URL": "https://i.pinimg.com/564x/1e/4e/b7/1e4eb724695f223d6fc018fdc1ee4e0f.jpg"
    },
    {
        "title": "Mecha Inosuke | Demon Slayer: Kimetsu no Yaiba",
        "description": "",
        "URL": "https://i.pinimg.com/564x/72/65/2f/72652fed327974dd17d336db83b3f73b.jpg"
    },
    {
        "title": "Kingdom of the WhiteMamba",
        "description": "Colored this MGS1 Cyborg Ninja Gray Fox",
        "URL": "https://i.pinimg.com/564x/c4/34/c8/c434c8b4ee494825d0feaf7dc967aba1.jpg"
    },
    {
        "title": "Iron Glove Sets, bamuth Lai",
        "description": "",
        "URL": "https://i.pinimg.com/564x/6b/4a/90/6b4a906facca6bd6e8a16f027838cd06.jpg"
    },
    {
        "title": "Kitsune",
        "description": "",
        "URL": "https://i.pinimg.com/564x/e7/1d/2f/e71d2f2a2e295d442140579112efef81.jpg"
    },
    {
        "title": "Litarnes",
        "description": "Dissociation with Fire",
        "URL": "https://i.pinimg.com/564x/dc/5b/1d/dc5b1d3f369157a309e564b7df99de90.jpg"
    },
    {
        "title": "",
        "description": "",
        "URL": "https://i.pinimg.com/564x/4f/a6/81/4fa68160fbaaa2828930ffdc9f515e65.jpg"
    },
    {
        "title": "Boy",
        "description": "iinsta-boyy, asian",
        "URL": "https://i.pinimg.com/564x/8c/51/a0/8c51a0a72b2f79f1b4c5e7bccb2d5070.jpg"
    },
    {
        "title": "Actor : Kim Kwon",
        "description": "ins : _____ripley",
        "URL": "https://i.pinimg.com/564x/4e/df/67/4edf67eadcd0d9b27bc1b8031cff25b3.jpg"
    },
    {
        "title": "Studio Model",
        "description": "Hunger games Capitol Realness Model Futuristic Clothes",
        "URL": "https://i.pinimg.com/564x/e9/97/17/e99717a3332b28120857d593e6ef1e24.jpg"
    },
    {
        "title": "Doctor",
        "description": "doctor by Siwoo Kim on ArtStation",
        "URL": "https://i.pinimg.com/564x/28/65/01/286501920334d591f6c456017490c91b.jpg"
    },
    {
        "title": "golden hour",
        "description": "",
        "URL": "https://i.pinimg.com/564x/c7/81/73/c78173f7149a0d4c59d7208752e3ac21.jpg"
    },
    {
        "title": "",
        "description": "#HONEYWORKS #Anime #Music #JPOP #Manga #Kawaii #animegirl #animeboy",
        "URL": "https://i.pinimg.com/564x/80/8e/6c/808e6cdd37281b17536bb0bab84d5b29.jpg"
    },
    {
        "title": "",
        "description": "",
        "URL": "https://i.pinimg.com/564x/cf/8a/7e/cf8a7e1561e784d0e714ded012eefa94.jpg"
    },
    {
        "title": "",
        "description": "",
        "URL": "https://i.pinimg.com/564x/fb/de/f2/fbdef298b9568c7a93265230409032d7.jpg"
    },
    {
        "title": "",
        "description": "",
        "URL": "https://i.pinimg.com/564x/06/15/8a/06158ae3b379f370e39b51a2d0273001.jpg"
    },
    {
        "title": "Mouth Practice",
        "description": "Practiced drawing a cartoon mouth",
        "URL": "https://i.pinimg.com/564x/81/c5/63/81c56356977e3f8f8f06e3c3e4a19bd9.jpg"
    },
    {
        "title": "Fall Outfit Inspos",
        "description": "Sven Vander Veken",
        "URL": "https://i.pinimg.com/564x/96/25/da/9625da973239279b9d6bf7b13df556f3.jpg"
    },
    {
        "title": "Pin by Gla on Mooodd uppp",
        "description": "Cute cartoon wallpapers, cute doodles, cute emoji wallpaper",
        "URL": "https://i.pinimg.com/564x/d5/3d/46/d53d469b068b791efe4526b4823856ed.jpg"
    },
    {
        "title": "Pin by :) on Harada",
        "description": "Art inspiration, Art reference, character art",
        "URL": "https://i.pinimg.com/564x/c5/25/f6/c525f6b4f31da29632c21c9f81cd678e.jpg"
    },
    {
        "title": "",
        "description": "",
        "URL": "https://i.pinimg.com/564x/de/8c/80/de8c8095c43f4bc5e47da12cc839ce2a.jpg"
    },
    {
        "title": "Keith Negley More",
        "description": "The Violence in Our Heads | Keith Negley More",
        "URL": "https://i.pinimg.com/474x/8c/09/70/8c09702f35265b2d6bdd80ec9588c440.jpg"
    },
    {
        "title": "Illustrations and Animatinos by Andrey Kasay",
        "description": "Let's explore the creative world of Andrey Kasay. Born and raised in east Russia, Andrey Kasay is an artist, illustrator and motion designer. Inspired by",
        "URL": "https://i.pinimg.com/564x/79/f6/a9/79f6a9c3ce1ff301a4726380abb4e7a7.jpg"
    },
    {
        "title": "",
        "description": "IG: girlygaaaal",
        "URL": "https://i.pinimg.com/564x/e7/2e/ef/e72eefe8c6ff83f49922ee22c4d36c76.jpg"
    },
    {
        "title": "",
        "description": "",
        "URL": "https://i.pinimg.com/564x/36/5a/47/365a47d1bd5f51dac6463458361882fa.jpg"
    },
    {
        "title": "Twitter",
        "description": "https://t.co/yqNHzmSpJh",
        "URL": "https://i.pinimg.com/564x/63/25/ad/6325ada8b58af4482167ce038b57fe69.jpg"
    },
    {
        "title": "Timothee Chalamet's Yassification",
        "description": "",
        "URL": "https://i.pinimg.com/564x/26/24/53/26245387328a35ae59987c5b4ae025d0.jpg"
    },
    {
        "title": "Xavier Serrano",
        "description": "Xavier Serrano",
        "URL": "https://i.pinimg.com/564x/07/4a/73/074a738d02e2ba06af2f728bd0babd58.jpg"
    },
    {
        "title": "Livia Falcaru - Illustrator and Visual Artist",
        "description": "Hello, I'm Livia — illustrator, visual artist and AR creator currently living and working in Bucharest, Romania. Welcome to my website & online shop!",
        "URL": "https://i.pinimg.com/564x/2b/89/3d/2b893dcb33ea1a32c92ce3c7be1d82af.jpg"
    }
]